setup.py
nykaa_mailer.egg-info/PKG-INFO
nykaa_mailer.egg-info/SOURCES.txt
nykaa_mailer.egg-info/dependency_links.txt
nykaa_mailer.egg-info/requires.txt
nykaa_mailer.egg-info/top_level.txt
src/CmdLineArgParser.py
src/NNRecMailer.py
src/__init__.py