Metadata-Version: 1.0
Name: nykaa-mailer
Version: 1.0
Summary: Generates the NN recommendations for Mailer
Home-page: UNKNOWN
Author: shubhang
Author-email: shubhang.malviya@daffodilsw.com
License: UNKNOWN
Platform: UNKNOWN
